flask_kombu/__init__.py
flask_kombu/flask_kombu.py
flask_kombu-0.1.0.dist-info/AUTHORS.rst
flask_kombu-0.1.0.dist-info/LICENSE
flask_kombu-0.1.0.dist-info/METADATA
flask_kombu-0.1.0.dist-info/WHEEL
flask_kombu-0.1.0.dist-info/top_level.txt
flask_kombu-0.1.0.dist-info/RECORD
