Metadata-Version: 2.1
Name: flask-kombu
Version: 0.1.0
Summary: Flask and Kombu integration.
Home-page: https://github.com/tchalupnik/flask_kombu
Author: Tomasz Chalupnik
Author-email: tchalupnik@gmail.com
License: MIT license
Keywords: flask_kombu
Platform: UNKNOWN
Classifier: Development Status :: 2 - Pre-Alpha
Classifier: Intended Audience :: Developers
Classifier: License :: OSI Approved :: MIT License
Classifier: Natural Language :: English
Classifier: Programming Language :: Python :: 3
Classifier: Programming Language :: Python :: 3.5
Classifier: Programming Language :: Python :: 3.6
Classifier: Programming Language :: Python :: 3.7
Classifier: Programming Language :: Python :: 3.8
Requires-Python: >=3.5
Requires-Dist: Flask
Requires-Dist: kombu
